README.md
setup.cfg
setup.py
polygon_lite.egg-info/PKG-INFO
polygon_lite.egg-info/SOURCES.txt
polygon_lite.egg-info/dependency_links.txt
polygon_lite.egg-info/top_level.txt
polygonlite/Edge.py
polygonlite/Operations.py
polygonlite/Point.py
polygonlite/Polygon.py
polygonlite/Services.py
polygonlite/__init__.py
polygonlite/config.py