Metadata-Version: 1.1
Name: polygon-lite
Version: 0.0.8.1
Summary: A lightweight module for polygon, edge and point operations.
Home-page: https://github.com/pranavtotla/polygonlite
Author: Pranav Totla
Author-email: UNKNOWN
License: MIT
Download-URL: https://github.com/pranavtotla/polygonlite/archive/v0.0.8.1.tar.gz
Platform: UNKNOWN
Classifier: Development Status :: 3 - Alpha
Classifier: Intended Audience :: Developers
Classifier: Programming Language :: Python :: 3
Classifier: Programming Language :: Python :: 2
